ilens_env_settings/__init__.py
env_settings2-5.4.2.dist-info/METADATA
env_settings2-5.4.2.dist-info/WHEEL
env_settings2-5.4.2.dist-info/top_level.txt
env_settings2-5.4.2.dist-info/RECORD
