Metadata-Version: 2.1
Name: env-settings2
Version: 5.4.2
Summary: UNKNOWN
Home-page: https://cloud.ilens.io
Author: irfanuddin
Author-email: irfanuddin@knowledgelens.com
License: Restricted
Platform: UNKNOWN
Requires-Dist: python-dotenv
Requires-Dist: pydantic
